mynk_etl/__init__.py
mynk_etl/extract/__init__.py
mynk_etl/extract/extract.py
mynk_etl/extract/kafkaExtract.py
mynk_etl/load/__init__.py
mynk_etl/load/fileWriter.py
mynk_etl/load/icebergWriter.py
mynk_etl/load/load.py
mynk_etl/load/rdbmsWriter.py
mynk_etl/main.py
mynk_etl/mainCalls/yfinanceUtils.py
mynk_etl/pyproject.toml
mynk_etl/sparkUtils/__init__.py
mynk_etl/sparkUtils/sparkComfunc.py
mynk_etl/sparkUtils/sparkInit.py
mynk_etl/transform/__init__.py
mynk_etl/transform/transform.py
mynk_etl/transform/yfinance/__init__.py
mynk_etl/transform/yfinance/tickTransform.py
mynk_etl/utils/common/__init__.py
mynk_etl/utils/common/confs.py
mynk_etl/utils/common/constants.py
mynk_etl/utils/common/genUtils.py
mynk_etl/utils/common/kUtils.py
mynk_etl/utils/common/marketUtils.py
mynk_etl/utils/logger/QueueListenerHandler.py
mynk_etl/utils/logger/__init__.py
mynk_etl/utils/logger/jsonLogging.py
mynk_etl/utils/logger/logDecor.py
mynk_etl/utils/logger/psgLogging.py
mynk_etl-0.1.14.dist-info/WHEEL
mynk_etl-0.1.14.dist-info/entry_points.txt
mynk_etl-0.1.14.dist-info/METADATA
mynk_etl-0.1.14.dist-info/RECORD
