Metadata-Version: 2.3
Name: mynk_etl
Version: 0.1.14
Summary: Add your description here
Requires-Dist: confluent-kafka~=2.6.0
Requires-Dist: fastavro>=1.10.0
Requires-Dist: ipykernel>=6.29.5
Requires-Dist: pandas-market-calendars>=5.2.4
Requires-Dist: pathlib>=1.0.1
Requires-Dist: psycopg2-binary>=2.9.11
Requires-Dist: pynessie>=0.67.0
Requires-Dist: pyspark==3.5.6
Requires-Dist: xxhash>=3.5.0
Requires-Dist: pytest>=7.4.0 ; extra == 'test'
Requires-Dist: pytest-mock>=3.11.0 ; extra == 'test'
Requires-Dist: pytest-cov>=4.1.0 ; extra == 'test'
Requires-Dist: pytest-asyncio>=0.21.0 ; extra == 'test'
Requires-Dist: pytest-xdist>=3.3.0 ; extra == 'test'
Requires-Dist: moto[s3]>=4.2.0 ; extra == 'test'
Requires-Python: >=3.11, <3.12
Provides-Extra: test
